MANIFEST.in
README.rst
bootstrap.py
buildout.cfg
setup.py
xbob/__init__.py
xbob.flandmark.egg-info/PKG-INFO
xbob.flandmark.egg-info/SOURCES.txt
xbob.flandmark.egg-info/dependency_links.txt
xbob.flandmark.egg-info/entry_points.txt
xbob.flandmark.egg-info/namespace_packages.txt
xbob.flandmark.egg-info/not-zip-safe
xbob.flandmark.egg-info/requires.txt
xbob.flandmark.egg-info/top_level.txt
xbob/flandmark/__init__.py
xbob/flandmark/flandmark_model.dat
xbob/flandmark/haarcascade_frontalface_alt.xml
xbob/flandmark/haarcascade_frontalface_alt2.xml
xbob/flandmark/test.py
xbob/flandmark/version.py
xbob/flandmark/ext/ext.cpp
xbob/flandmark/ext/flandmark_detector.cpp
xbob/flandmark/ext/flandmark_detector.h
xbob/flandmark/ext/liblbp.cpp
xbob/flandmark/ext/liblbp.h
xbob/flandmark/script/__init__.py
xbob/flandmark/script/annotate.py