Metadata-Version: 1.1
Name: xbob.flandmark
Version: 1.0.10
Summary: Python bindings to the flandmark keypoint localization library
Home-page: http://pypi.python.org/pypi/xbob.flandmark
Author: Andre Anjos
Author-email: andre.anjos@idiap.ch
License: GPLv3
Platform: UNKNOWN
Classifier: Development Status :: 5 - Production/Stable
Classifier: Intended Audience :: Developers
Classifier: License :: OSI Approved :: GNU General Public License v3 (GPLv3)
Classifier: Natural Language :: English
Classifier: Programming Language :: Python
Classifier: Topic :: Scientific/Engineering :: Artificial Intelligence
